bpandas/__init__.py
bpandas/bgraphics.py
bpandas/btables.py
bpandas-0.1.7.dist-info/LICENSE
bpandas-0.1.7.dist-info/METADATA
bpandas-0.1.7.dist-info/WHEEL
bpandas-0.1.7.dist-info/RECORD
