Metadata-Version: 2.3
Name: bpandas
Version: 0.1.7
Summary: Funções utilitárias para facilitar o uso do pandas
License: MIT
Keywords: pandas,dataframe,frequencies,statistics,utility
Author: David Closs
Author-email: davidcloss@live.com
Requires-Python: >=3.13,<3.14
Classifier: License :: OSI Approved :: MIT License
Classifier: Operating System :: OS Independent
Classifier: Programming Language :: Python :: 3
Classifier: Programming Language :: Python :: 3.13
Classifier: Topic :: Scientific/Engineering :: Information Analysis
Requires-Dist: matplotlib (==3.10.5)
Requires-Dist: numpy (==2.3.2)
Requires-Dist: pandas (==2.3.1)
Project-URL: Homepage, https://github.com/davidcloss/bpandas
Project-URL: Issues, https://github.com/davidcloss/bpandas/issues
Project-URL: Repository, https://github.com/davidcloss/bpandas
